{
  "pages" : {  
    "homepage" : { 
      "url" : "/" 
     },

    "schema" : {
      "url" : "/schema"
    },

    "type" : {
      "url" :"{type}"
    },

    "type_schema" : { 
      "url" : "{type}?schema"
    },

    "type_inspect" : {
      "url" : "{type}?inspect"
    },

    "domain" : {
      "url" : "{domain}"
    },

    "domain_schema" : { 
      "url" : "{domain}?schema"
    },

    "domain_community" : {
      "url" : "{domain}?community"
    },

    "domain_inspect" : {
      "url" : "{domain}?inspect"
    },

    "apps" : {
      "url" : "/apps"
    },

    "app_details" : {
      "url" : "{app}?apps"
    },

    "user" : {
      "url" : "{user}"
    },

    "user_queries" : {
        "url" : "{user}?queries"
    },

    "user_apps" : {
        "url" : "{user}?apps"
    },

    "user_inspect" : {
        "url" : "{user}?inspect"
    },

    "topic" : {
        "url" : "{topic}"
    },
      
    "topic_web" : {
      "url" : "{topic}?web"
    },

    "topic_inspect" : {
      "url" : "{topic}?inspect"
    },

    "explore" : {
      "url" : "/explore"
    },

    "topicapi_full_nolang" : {
      "url" : "/api/experimental/topic/full{topic_slow_2}"
    },

    "topicapi_full_multilang" : {
      "url" : "/api/experimental/topic/full{topic_slow_2}?lang=/lang/en&lang=/lang/wp"
    },

    "topicapi_full" : {
      "url" : "/api/experimental/topic/full{topic_slow_2}?lang=/lang/en"
    },

    "topicapi_standard" : {
      "url" : "/api/experimental/topic/standard{topic_slow_2}"
    },
    "helloworldfreebase" : { 
      "url" : "/sample/hello"
    },
    "helloworldsite" : {
      "url" : "/sample/helloworld"
    },  
    "tos" : { 
      "url" : "/policies/tos"
    },
    "helloworldtopicapi" : { 
      "url" : "/sample/topicapi?id={topic_slow_2}"
    },
    "helloworldacre" : {
      "url" : "/_helloworld"
    },
    "sorter" : { 
      "url" : "/sorter"
    },
    "glatency" : { 
      "url" : "/helloappengine"
    }
    
  },

  "tests" : {
    "small" : { 
      "pages" : [
        { "page" : "explore", "repeat" : 10 },
        { "page" : "topic", "repeat" : 50 },
        { "page" : "topic_web", "repeat" : 10 },
        { "page" : "type_inspect", "repeat" : 5 },
        { "page" : "topic_inspect", "repeat" : 10 },
        { "page" : "domain_inspect", "repeat" : 5 },
        { "page" : "schema", "repeat" : 5 },
        { "page" : "type_schema", "repeat" : 10 },
        { "page" : "domain_schema", "repeat" : 5 },
        { "page" : "domain", "repeat" : 5 },
        { "page" : "type", "repeat" : 10 },
        { "page" : "user", "repeat" : 5 },
        { "page" : "domain_community", "repeat" : 5 },
        { "page" : "apps", "repeat" : 5 },
        { "page" : "app_details", "repeat" : 5 },
        { "page" : "homepage","repeat" : 5 }
      ],
      "random" : true
    },

    "medium" : {
        "parent" : "small",
        "weight" : 4,
        "random" : false
    },  

    "large" : {
        "parent" : "small",
        "weight" : 10,
        "random" : true
    },

    "schema" : {
      "pages" : [
        {
          "page" : "schema",
          "repeat" : 10
        },

        {
          "page" : "type_schema",
          "repeat" : 10
        },

        {
          "page" : "domain_schema",
          "repeat" : 10
        }

      ],
      "random" : false
    }
  }


}